setup.py
termdic/__init__.py
termdic/termdic.py
termdic.egg-info/PKG-INFO
termdic.egg-info/SOURCES.txt
termdic.egg-info/dependency_links.txt
termdic.egg-info/entry_points.txt
termdic.egg-info/not-zip-safe
termdic.egg-info/requires.txt
termdic.egg-info/top_level.txt