Metadata-Version: 1.0
Name: termdic
Version: 0.1.1
Summary: Dictionary in your terminal
Home-page: https://github.com/hzwer/termdic
Author: hzwer
Author-email: UNKNOWN
License: UNKNOWN
Keywords: dictionary,terminal
Platform: UNKNOWN
